setup.py
allauth_hatena/__init__.py
allauth_hatena/provider.py
allauth_hatena/urls.py
allauth_hatena/views.py
django_allauth_hatena.egg-info/PKG-INFO
django_allauth_hatena.egg-info/SOURCES.txt
django_allauth_hatena.egg-info/dependency_links.txt
django_allauth_hatena.egg-info/requires.txt
django_allauth_hatena.egg-info/top_level.txt