Metadata-Version: 1.1
Name: django-allauth-hatena
Version: 0.1.2
Summary: Allauth provider for hatena OAuth
Home-page: https://github.com/h3poteto/django-allauth-hatena
Author: h3poteto
Author-email: h3.poteto@gmail.com
License: MIT
Keywords: allauth hatena
Platform: UNKNOWN
Classifier: License :: OSI Approved :: MIT License
Classifier: Programming Language :: Python :: 3
Classifier: Programming Language :: Python :: 3.4
Classifier: Programming Language :: Python :: 3.5
Classifier: Programming Language :: Python :: 3.6
Classifier: Programming Language :: Python :: Implementation :: CPython
Classifier: Programming Language :: Python :: Implementation :: PyPy
